leveelogic/__init__.py
leveelogic/geolib/dstability_model_helper.py
leveelogic/helpers.py
leveelogic/objects/__init__.py
leveelogic/settings.py
leveelogic_slim-0.0.2.dist-info/METADATA
leveelogic_slim-0.0.2.dist-info/WHEEL
leveelogic_slim-0.0.2.dist-info/RECORD
