Metadata-Version: 2.3
Name: leveelogic_slim
Version: 0.0.2
Summary: Leveelogic slim version
Author: Rob van Putten
Author-email: breinbaasnl@gmail.com
Requires-Python: >=3.12,<4.0
Classifier: Programming Language :: Python :: 3
Classifier: Programming Language :: Python :: 3.12
Classifier: Programming Language :: Python :: 3.13
Requires-Dist: d-geolib (>=2.6.0,<3.0.0)
Requires-Dist: pytest (>=8.3.5,<9.0.0)
